pypanasonic/__about__.py
pypanasonic/__init__.py
pypanasonic/mewtocol.py
pypanasonic-0.0.8.dist-info/METADATA
pypanasonic-0.0.8.dist-info/WHEEL
pypanasonic-0.0.8.dist-info/licenses/LICENSE
pypanasonic-0.0.8.dist-info/licenses/LICENSE.txt
pypanasonic-0.0.8.dist-info/RECORD
