Metadata-Version: 2.3
Name: pypanasonic
Version: 0.0.8
Summary: Panasonic PLC mewtocol lib via serial port
Project-URL: Homepage, https://github.com/hy1stax/pypanasonic
Project-URL: Source, https://github.com/hy1stax/pypanasonic
Author-email: hy1stax <luweizhao09@gmail.com>
License-Expression: MIT
License-File: LICENSE
License-File: LICENSE.txt
Keywords: Mewtocol,PLC,Panasonic,Protocol,Serial
Classifier: Development Status :: 4 - Beta
Classifier: Programming Language :: Python
Classifier: Programming Language :: Python :: 3.8
Classifier: Programming Language :: Python :: 3.9
Classifier: Programming Language :: Python :: 3.10
Classifier: Programming Language :: Python :: 3.11
Classifier: Programming Language :: Python :: 3.12
Classifier: Programming Language :: Python :: Implementation :: CPython
Classifier: Programming Language :: Python :: Implementation :: PyPy
Requires-Python: >=3.8
Requires-Dist: pyserial
Requires-Dist: regex
